setup.py
cmds/__init__.py
cmds/gentest.py
cmds/helper.py
cmds/profile.py
cmds/repl.py
cmds/stat.py
hangulize/__init__.py
hangulize/hangul.py
hangulize/models.py
hangulize/normalization.py
hangulize/processing.py
hangulize.egg-info/PKG-INFO
hangulize.egg-info/SOURCES.txt
hangulize.egg-info/dependency_links.txt
hangulize.egg-info/not-zip-safe
hangulize.egg-info/requires.txt
hangulize.egg-info/top_level.txt
hangulize/langs/__init__.py
hangulize/langs/aze/__init__.py
hangulize/langs/bel/__init__.py
hangulize/langs/bul/__init__.py
hangulize/langs/cat/__init__.py
hangulize/langs/ces/__init__.py
hangulize/langs/cym/__init__.py
hangulize/langs/deu/__init__.py
hangulize/langs/ell/__init__.py
hangulize/langs/epo/__init__.py
hangulize/langs/est/__init__.py
hangulize/langs/fin/__init__.py
hangulize/langs/grc/__init__.py
hangulize/langs/hbs/__init__.py
hangulize/langs/hun/__init__.py
hangulize/langs/isl/__init__.py
hangulize/langs/ita/__init__.py
hangulize/langs/jpn/__init__.py
hangulize/langs/kat/__init__.py
hangulize/langs/kat/narrow.py
hangulize/langs/lat/__init__.py
hangulize/langs/lav/__init__.py
hangulize/langs/lit/__init__.py
hangulize/langs/mkd/__init__.py
hangulize/langs/nld/__init__.py
hangulize/langs/pol/__init__.py
hangulize/langs/por/__init__.py
hangulize/langs/por/br.py
hangulize/langs/ron/__init__.py
hangulize/langs/rus/__init__.py
hangulize/langs/slk/__init__.py
hangulize/langs/slv/__init__.py
hangulize/langs/spa/__init__.py
hangulize/langs/sqi/__init__.py
hangulize/langs/swe/__init__.py
hangulize/langs/tur/__init__.py
hangulize/langs/ukr/__init__.py
hangulize/langs/vie/__init__.py
hangulize/langs/wlm/__init__.py
tests/__init__.py
tests/aze.py
tests/bel.py
tests/bul.py
tests/cat.py
tests/ces.py
tests/cym.py
tests/deu.py
tests/ell.py
tests/epo.py
tests/est.py
tests/fin.py
tests/grc.py
tests/hbs.py
tests/hun.py
tests/internal.py
tests/isl.py
tests/ita.py
tests/jpn.py
tests/kat.py
tests/kat_narrow.py
tests/lat.py
tests/lav.py
tests/lit.py
tests/mkd.py
tests/nld.py
tests/pol.py
tests/por.py
tests/por_br.py
tests/ron.py
tests/rus.py
tests/slk.py
tests/slv.py
tests/spa.py
tests/sqi.py
tests/swe.py
tests/tur.py
tests/ukr.py
tests/vie.py
tests/wlm.py